{
    "url": "https://shop.hobel.ch/produkt/schwab-partner-barhocker/",
    "title": "Schwab + Partner – Barhocker",
    "description": "Nussbaum FSC zertifiziert, massiv, mit Leinöl geölt Fussring in Chromstahl geschliffen (in diversen Holzarten erhältlich) siehe Register Holzarten Lieferfrist: 2-3 Tage",
    "article_no": "79",
    "price": "CHF1'070.00",
    "variations": null,
    "image": "https://shop.hobel.ch/wp-content/uploads/2019/01/Schwab-Partner-–-Barhocker-1.jpg",
    "slug": "schwab-partner-barhocker",
    "scraped_at": "2025-12-01T20:42:21+00:00",
    "category": "Hocker"
}